{
  "name": "donwload-image",
  "nodes": [
    {
      "parameters": {},
      "type": "n8n-nodes-base.manualTrigger",
      "typeVersion": 1,
      "position": [
        -528,
        256
      ],
      "id": "79ff587a-6833-41d2-9c09-cac9b75da0d0",
      "name": "When clicking ‘Execute workflow’"
    },
    {
      "parameters": {
        "amount": 2
      },
      "type": "n8n-nodes-base.wait",
      "typeVersion": 1.1,
      "position": [
        912,
        240
      ],
      "id": "4928a0b0-f2aa-48e5-8476-f9676093ede3",
      "name": "Wait1",
      "webhookId": "f2a645e4-8503-4c5b-a804-bad8da20fc69"
    },
    {
      "parameters": {
        "operation": "compress",
        "binaryPropertyName": "={{ $json.binary_keys }}",
        "outputFormat": "zip",
        "fileName": "images.zip"
      },
      "name": "Compression",
      "type": "n8n-nodes-base.compression",
      "position": [
        512,
        496
      ],
      "typeVersion": 1,
      "id": "f42851b5-5ecd-4290-b07d-a3b02230c901"
    },
    {
      "parameters": {
        "batchSize": 1,
        "options": {}
      },
      "id": "b17e5395-e445-4832-93ae-add599723b86",
      "name": "Split In Batches",
      "type": "n8n-nodes-base.splitInBatches",
      "typeVersion": 2,
      "position": [
        48,
        256
      ]
    },
    {
      "parameters": {
        "jsCode": "items.forEach(item => {\n  if (item.json?.Link) {\n    item.json.Link = item.json.Link.trim();\n  }\n});\n\nreturn items;"
      },
      "type": "n8n-nodes-base.code",
      "typeVersion": 2,
      "position": [
        -128,
        256
      ],
      "id": "242628f3-b198-4be8-8a63-efcf0941df39",
      "name": "Code"
    },
    {
      "parameters": {
        "url": "={{ $json.Link }}",
        "options": {
          "redirect": {
            "redirect": {
              "maxRedirects": "=true"
            }
          },
          "response": {
            "response": {
              "responseFormat": "file"
            }
          },
          "timeout": 300000
        }
      },
      "type": "n8n-nodes-base.httpRequest",
      "typeVersion": 4,
      "position": [
        304,
        240
      ],
      "id": "4688438f-d91e-4e27-beaf-6eecc355286c",
      "name": "Download File"
    },
    {
      "parameters": {
        "documentId": {
          "__rl": true,
          "value": "1bLC6KATMOi7uZri1jCHYvdnBGAmYOpPsmMs0oxHWM4E",
          "mode": "list",
          "cachedResultName": "List-url",
          "cachedResultUrl": "https://docs.google.com/spreadsheets/d/1bLC6KATMOi7uZri1jCHYvdnBGAmYOpPsmMs0oxHWM4E/edit?usp=drivesdk"
        },
        "sheetName": {
          "__rl": true,
          "value": 708467874,
          "mode": "list",
          "cachedResultName": "Sheet2",
          "cachedResultUrl": "https://docs.google.com/spreadsheets/d/1bLC6KATMOi7uZri1jCHYvdnBGAmYOpPsmMs0oxHWM4E/edit#gid=708467874"
        },
        "options": {}
      },
      "type": "n8n-nodes-base.googleSheets",
      "typeVersion": 4.7,
      "position": [
        -336,
        256
      ],
      "id": "857d8e2b-f479-4dda-b044-cad73fec9e91",
      "name": "Get row(s) in sheet",
      "credentials": {
        "googleSheetsOAuth2Api": {
          "id": "Y4W0pcwPu2sfk8N1",
          "name": "Google Sheets account"
        }
      }
    },
    {
      "parameters": {
        "jsCode": "let binaries = {}, binary_keys = [];\n\nfor([index, item] of items.entries()) {\n    binaries[`data_${index}`] = item.binary.data;\n    binary_keys.push(`data_${index}`);\n}\n\nreturn [{\n    json: {\n        binary_keys: binary_keys.join(',')\n    },\n    binary: binaries\n}];"
      },
      "type": "n8n-nodes-base.code",
      "typeVersion": 2,
      "position": [
        304,
        496
      ],
      "id": "1fb0c57e-2834-4277-a354-084f9054d46f",
      "name": "merge"
    }
  ],
  "pinData": {
    "When clicking ‘Execute workflow’": [
      {
        "json": {}
      }
    ]
  },
  "connections": {
    "When clicking ‘Execute workflow’": {
      "main": [
        [
          {
            "node": "Get row(s) in sheet",
            "type": "main",
            "index": 0
          }
        ]
      ]
    },
    "Wait1": {
      "main": [
        [
          {
            "node": "Split In Batches",
            "type": "main",
            "index": 0
          }
        ]
      ]
    },
    "Split In Batches": {
      "main": [
        [
          {
            "node": "Download File",
            "type": "main",
            "index": 0
          }
        ],
        [
          {
            "node": "merge",
            "type": "main",
            "index": 0
          }
        ]
      ]
    },
    "Code": {
      "main": [
        [
          {
            "node": "Split In Batches",
            "type": "main",
            "index": 0
          }
        ]
      ]
    },
    "Download File": {
      "main": [
        [
          {
            "node": "Wait1",
            "type": "main",
            "index": 0
          }
        ]
      ]
    },
    "Get row(s) in sheet": {
      "main": [
        [
          {
            "node": "Code",
            "type": "main",
            "index": 0
          }
        ]
      ]
    },
    "merge": {
      "main": [
        [
          {
            "node": "Compression",
            "type": "main",
            "index": 0
          }
        ]
      ]
    }
  },
  "active": false,
  "settings": {
    "executionOrder": "v1"
  },
  "versionId": "48111dd0-5495-429b-bc65-cd947abd4e9e",
  "meta": {
    "templateCredsSetupCompleted": true,
    "instanceId": "dcfade3f45b590d9e21d93325377795897ae808c2e6bce95efc9aea7a8036207"
  },
  "id": "l4E1RkmqVC20yG3k",
  "tags": []
}
